chowda-0.4.0.dist-info/METADATA
chowda-0.4.0.dist-info/WHEEL
chowda/__init__.py
chowda/_version.py
chowda/admin.py
chowda/api.py
chowda/app.py
chowda/auth/__init__.py
chowda/auth/oauth.py
chowda/auth/utils.py
chowda/config.py
chowda/db.py
chowda/fields.py
chowda/flows/__init__.py
chowda/flows/ingest.py
chowda/log.py
chowda/models.py
chowda/routers/__init__.py
chowda/routers/dashboard.py
chowda/routers/events.py
chowda/routers/sony_ci.py
chowda/utils.py
chowda/views.py
chowda-0.4.0.dist-info/RECORD
