Metadata-Version: 2.1
Name: chowda
Version: 0.4.0
Summary: A CLAMS processing application
Home-page: https://github.com/WGBH-MLA/chowda
Author-Email: WGBH-MLA <ryan_harbert@wgbh.org>
License: MIT
Project-URL: Homepage, https://github.com/WGBH-MLA/chowda
Project-URL: Documentation, https://WGBH-MLA.github.io/chowda/
Project-URL: Repository, https://github.com/WGBH-MLA/chowda
Requires-Python: <4.0,>=3.8.1
Requires-Dist: fastapi~=0.103
Requires-Dist: starlette-admin~=0.11
Requires-Dist: sqlmodel~=0.0
Requires-Dist: pydantic[email]~=1.10
Requires-Dist: sonyci~=0.1
Requires-Dist: psycopg2~=2.9
Requires-Dist: metaflow~=2.9
Requires-Dist: alembic~=1.12
Requires-Dist: python-dotenv~=1.0
Requires-Dist: authlib~=1.2
Requires-Dist: itsdangerous~=2.1
Requires-Dist: httpx~=0.25
Requires-Dist: rich~=13.5
Requires-Dist: uvicorn[standard]~=0.23; extra == "production"
Requires-Dist: gunicorn~=21.2; extra == "production"
Requires-Dist: factory-boy~=3.3; extra == "test"
Requires-Dist: pytest~=7.4; extra == "test"
Requires-Dist: pytest-cov~=4.1; extra == "test"
Requires-Dist: pytest-sugar~=0.9; extra == "test"
Requires-Dist: pytest-xdist~=3.3; extra == "test"
Requires-Dist: httpx~=0.25; extra == "test"
Requires-Dist: nbmake~=1.4; extra == "test"
Requires-Dist: vcrpy~=5.1; extra == "test"
Requires-Dist: pytest-vcr~=1.0; extra == "test"
Requires-Dist: urllib3~=1.26; extra == "test"
Requires-Dist: pytest-mock~=3.11; extra == "test"
Requires-Dist: pytest-asyncio~=0.21; extra == "test"
Requires-Dist: trio~=0.22; extra == "test"
Requires-Dist: locust~=2.16; extra == "locust"
Requires-Dist: pydantic-factories~=1.17; extra == "locust"
Requires-Dist: kubernetes~=28.1; extra == "development"
Provides-Extra: production
Provides-Extra: test
Provides-Extra: locust
Provides-Extra: development
